database_automation/__init__.py
database_automation/mongo_crud.py
database_automation_sample_package-0.0.7.dist-info/METADATA
database_automation_sample_package-0.0.7.dist-info/WHEEL
database_automation_sample_package-0.0.7.dist-info/top_level.txt
database_automation_sample_package-0.0.7.dist-info/RECORD
